agentbible/__init__.py
agentbible/__main__.py
agentbible/errors.py
agentbible/py.typed
agentbible/cli/__init__.py
agentbible/cli/audit.py
agentbible/cli/ci.py
agentbible/cli/init.py
agentbible/cli/main.py
agentbible/cli/validate.py
agentbible/context/__init__.py
agentbible/context/chunker.py
agentbible/context/config.py
agentbible/context/manager.py
agentbible/domains/__init__.py
agentbible/domains/quantum/__init__.py
agentbible/domains/quantum/errors.py
agentbible/domains/quantum/validators.py
agentbible/philosophy/__init__.py
agentbible/philosophy/principles.py
agentbible/provenance/__init__.py
agentbible/provenance/hdf5.py
agentbible/templates/__init__.py
agentbible/templates/cpp_hpc/.cursorrules
agentbible/templates/cpp_hpc/CMakeLists.txt.template
agentbible/templates/cpp_hpc/README.md.template
agentbible/templates/cpp_hpc/include/CudaMemory.hpp
agentbible/templates/cpp_hpc/include/core.hpp
agentbible/templates/cpp_hpc/src/core.cpp
agentbible/templates/cpp_hpc/src/main.cpp
agentbible/templates/cpp_hpc/tests/test_core.cpp
agentbible/templates/cpp_hpc/tests/test_cuda_memory.cpp
agentbible/templates/cpp_hpc/tests/test_main.cpp
agentbible/templates/python_research/.cursorrules
agentbible/templates/python_research/README.md.template
agentbible/templates/python_research/pyproject.toml.template
agentbible/templates/python_research/src/__init__.py
agentbible/templates/python_research/src/validation.py
agentbible/templates/python_research/tests/__init__.py
agentbible/templates/python_research/tests/conftest.py
agentbible/templates/python_research/tests/test_validation.py
agentbible/testing/__init__.py
agentbible/testing/decorators.py
agentbible/testing/fixtures.py
agentbible/validators/__init__.py
agentbible/validators/base.py
agentbible/validators/bounds.py
agentbible/validators/probability.py
agentbible-0.3.0.dist-info/METADATA
agentbible-0.3.0.dist-info/WHEEL
agentbible-0.3.0.dist-info/entry_points.txt
agentbible-0.3.0.dist-info/licenses/LICENSE
agentbible-0.3.0.dist-info/RECORD
