Metadata-Version: 2.4
Name: agentbible
Version: 0.3.0
Summary: One-shot correct infrastructure for AI agents working on scientific code
Project-URL: Homepage, https://github.com/rylanmalarchick/research-code-principles
Project-URL: Documentation, https://github.com/rylanmalarchick/research-code-principles#readme
Project-URL: Repository, https://github.com/rylanmalarchick/research-code-principles.git
Project-URL: Issues, https://github.com/rylanmalarchick/research-code-principles/issues
Project-URL: Changelog, https://github.com/rylanmalarchick/research-code-principles/blob/main/CHANGELOG.md
Author-email: Rylan Malarchick <rylan1012@gmail.com>
Maintainer-email: Rylan Malarchick <rylan1012@gmail.com>
License-Expression: MIT
License-File: LICENSE
Keywords: ai-coding,developer-tools,physics,quantum,research,scientific-computing,validation
Classifier: Development Status :: 3 - Alpha
Classifier: Environment :: Console
Classifier: Intended Audience :: Developers
Classifier: Intended Audience :: Science/Research
Classifier: License :: OSI Approved :: MIT License
Classifier: Operating System :: OS Independent
Classifier: Programming Language :: Python :: 3
Classifier: Programming Language :: Python :: 3.9
Classifier: Programming Language :: Python :: 3.10
Classifier: Programming Language :: Python :: 3.11
Classifier: Programming Language :: Python :: 3.12
Classifier: Topic :: Scientific/Engineering
Classifier: Topic :: Scientific/Engineering :: Physics
Classifier: Topic :: Software Development :: Libraries :: Python Modules
Classifier: Topic :: Software Development :: Quality Assurance
Classifier: Typing :: Typed
Requires-Python: >=3.9
Requires-Dist: click>=8.0
Requires-Dist: numpy>=1.20
Requires-Dist: pyyaml>=6.0
Requires-Dist: rich>=13.0
Provides-Extra: all
Requires-Dist: chromadb>=0.4; extra == 'all'
Requires-Dist: h5py>=3.0; extra == 'all'
Requires-Dist: hypothesis>=6.0; extra == 'all'
Requires-Dist: mypy>=1.0; extra == 'all'
Requires-Dist: openai>=1.0; extra == 'all'
Requires-Dist: pre-commit>=3.0; extra == 'all'
Requires-Dist: pytest-cov>=4.0; extra == 'all'
Requires-Dist: pytest-xdist>=3.0; extra == 'all'
Requires-Dist: pytest>=7.0; extra == 'all'
Requires-Dist: ruff>=0.1; extra == 'all'
Requires-Dist: tiktoken>=0.5; extra == 'all'
Requires-Dist: types-pyyaml>=6.0; extra == 'all'
Provides-Extra: context
Requires-Dist: chromadb>=0.4; extra == 'context'
Requires-Dist: openai>=1.0; extra == 'context'
Requires-Dist: tiktoken>=0.5; extra == 'context'
Provides-Extra: dev
Requires-Dist: hypothesis>=6.0; extra == 'dev'
Requires-Dist: mypy>=1.0; extra == 'dev'
Requires-Dist: pre-commit>=3.0; extra == 'dev'
Requires-Dist: pytest-cov>=4.0; extra == 'dev'
Requires-Dist: pytest-xdist>=3.0; extra == 'dev'
Requires-Dist: pytest>=7.0; extra == 'dev'
Requires-Dist: ruff>=0.1; extra == 'dev'
Requires-Dist: types-pyyaml>=6.0; extra == 'dev'
Provides-Extra: hdf5
Requires-Dist: h5py>=3.0; extra == 'hdf5'
Provides-Extra: quantum
Provides-Extra: vector
Requires-Dist: chromadb>=0.4; extra == 'vector'
Requires-Dist: openai>=1.0; extra == 'vector'
Requires-Dist: tiktoken>=0.5; extra == 'vector'
